Metadata-Version: 1.0
Name: ylin-distributions
Version: 0.1
Summary: Gaussian and Binomial distributions
Home-page: UNKNOWN
Author: Yu-Huai Lin
Author-email: yuhuailin0323@gmail.com
License: UNKNOWN
Platform: UNKNOWN
